arivo/api/__init__.py
arivo/api/http.py
arivo/api/json.py
arivo_api-1.1.2.dist-info/AUTHORS
arivo_api-1.1.2.dist-info/LICENSE
arivo_api-1.1.2.dist-info/METADATA
arivo_api-1.1.2.dist-info/WHEEL
arivo_api-1.1.2.dist-info/pbr.json
arivo_api-1.1.2.dist-info/top_level.txt
arivo_api-1.1.2.dist-info/RECORD
