Metadata-Version: 2.1
Name: arivo-api
Version: 1.1.2
Summary: Python package for interacting with the ARIVO api
Home-page: https://gitlab.com/arivo-public/api.git
Author: ARIVO
Author-email: support@arivo.co
License: MIT
Keywords: arivo webhook api
Classifier: Intended Audience :: Developers
Classifier: License :: OSI Approved :: MIT License
Classifier: Programming Language :: Python
Classifier: Programming Language :: Python :: 3.6
Classifier: Programming Language :: Python :: 3.7
Classifier: Programming Language :: Python :: 3.8
License-File: LICENSE
License-File: AUTHORS
Requires-Dist: arivo (<2,>=1.0.3)
Requires-Dist: requests (<3,>=2.24)
